privsci_client/__init__.py
privsci_client/accounts.py
privsci_client/base.py
privsci_client/client.py
privsci_client/config_store.py
privsci_client/database.py
privsci_client/groups.py
privsci_client/http.py
privsci_client/keys.py
privsci_client/models.py
privsci_client/actions/__init__.py
privsci_client/actions/check.py
privsci_client/actions/create.py
privsci_client/actions/export.py
privsci_client/actions/sign.py
privsci_client/actions/verify.py
privsci_client/actions/helpers/handle_serialize.py
privsci_client/actions/helpers/package_proof.py
privsci_client/actions/helpers/package_sth.py
privsci_client/actions/helpers/registry.py
privsci_client/actions/helpers/verifier.py
privsci_client/actions/helpers/handlers/molecule_smiles.py
privsci_client/cli/accounts_cli.py
privsci_client/cli/config_cli.py
privsci_client/cli/groups_cli.py
privsci_client/cli/keys_cli.py
privsci_client/cli/main.py
privsci-0.0.5.dist-info/METADATA
privsci-0.0.5.dist-info/WHEEL
privsci-0.0.5.dist-info/entry_points.txt
privsci-0.0.5.dist-info/top_level.txt
privsci-0.0.5.dist-info/RECORD
