Metadata-Version: 2.4
Name: privsci
Version: 0.0.5
Summary: Client library for the PrivSci platform
Requires-Python: >=3.8
Requires-Dist: requests
Requires-Dist: typer
Requires-Dist: pydantic
Requires-Dist: rdkit
